{
    "player": {
        "discord_nickname": "lezz.xxx#6182",
        "dst_nickname": "murrr."
    },
    "items": [
        {
            "name": "Корону просветления",
            "id": "alterguardianhat"
        },
        {
            "name": "Мешок крампуса",
            "id": "krampus_sack"
        },
        {
            "name": "Будильные часы",
            "id": "pocketwatch_weapon"
        }
    ],
    "status": "executed",
    "created_at": "2022-12-30 12:49:39.777000+00:00",
    "approved_at": "2023-01-02 10:13:16.342000+00:00",
    "executed_at": "2023-01-02 10:27:20.860000+00:00",
    "path": "Оазис Кошмаров_2022-12-30 08:17:36.936000+00:00"
}